cassa/classification_pipeline.py
cassa/distance_matrix.py
cassa-2.1.1.dist-info/LICENSE
cassa-2.1.1.dist-info/WHEEL
cassa-2.1.1.dist-info/METADATA
cassa-2.1.1.dist-info/RECORD
