Metadata-Version: 2.1
Name: cassa
Version: 2.1.1
Summary: Python package to perform unsupervised and semi-supervised machine learning (ML) classification algorithms on generic tensors of pre-processed data
License: MIT
Author: Karl Nordstrom
Author-email: karl.am.nordstrom@gmail.com
Requires-Python: >=3.8,<3.11
Classifier: License :: OSI Approved :: MIT License
Classifier: Programming Language :: Python :: 3
Classifier: Programming Language :: Python :: 3.10
Classifier: Programming Language :: Python :: 3.8
Classifier: Programming Language :: Python :: 3.9
Provides-Extra: docs
Provides-Extra: progress
Requires-Dist: numpy (>=1.22.3,<2.0.0)
Requires-Dist: progress (>=1.6,<2.0); extra == "progress"
Requires-Dist: scikit-learn (>=1.0.2,<2.0.0)
Requires-Dist: scipy (>=1.8.0,<2.0.0)
Requires-Dist: seaborn (>=0.11.2,<0.12.0)
